{
  "buildFiles": [
    "C:\\Users\\Leandro\\dev\\flutter\\packages\\flutter_tools\\gradle\\src\\main\\groovy\\CMakeLists.txt"
  ],
  "cleanCommandsComponents": [
    [
      "C:\\Users\\Leandro\\AppData\\Local\\Android\\sdk\\cmake\\3.22.1\\bin\\ninja.exe",
      "-C",
      "C:\\Users\\Leandro\\Documents\\GitHub\\m08-uf1-multimedia-leandro-joancarlos\\camera_on_flutter\\android\\app\\.cxx\\RelWithDebInfo\\3y3d6p5t\\x86_64",
      "clean"
    ]
  ],
  "buildTargetsCommandComponents": [
    "C:\\Users\\Leandro\\AppData\\Local\\Android\\sdk\\cmake\\3.22.1\\bin\\ninja.exe",
    "-C",
    "C:\\Users\\Leandro\\Documents\\GitHub\\m08-uf1-multimedia-leandro-joancarlos\\camera_on_flutter\\android\\app\\.cxx\\RelWithDebInfo\\3y3d6p5t\\x86_64",
    "{LIST_OF_TARGETS_TO_BUILD}"
  ],
  "libraries": {},
  "toolchains": {
    "toolchain": {
      "cCompilerExecutable": "C:\\Users\\Leandro\\AppData\\Local\\Android\\Sdk\\ndk\\27.0.12077973\\toolchains\\llvm\\prebuilt\\windows-x86_64\\bin\\clang.exe",
      "cppCompilerExecutable": "C:\\Users\\Leandro\\AppData\\Local\\Android\\Sdk\\ndk\\27.0.12077973\\toolchains\\llvm\\prebuilt\\windows-x86_64\\bin\\clang++.exe"
    }
  },
  "cFileExtensions": [],
  "cppFileExtensions": []
}